pycarbond/__init__.py
pycarbond/constants.py
pycarbond/fs.py
pycarbond/lib.py
pycarbond-0.1.0.dist-info/METADATA
pycarbond-0.1.0.dist-info/WHEEL
pycarbond-0.1.0.dist-info/RECORD
